streamlit_app_generator/__init__.py
streamlit_app_generator/cli.py
streamlit_app_generator/generator.py
streamlit_app_generator/wizard.py
streamlit_app_generator/config/__init__.py
streamlit_app_generator/config/app_config.py
streamlit_app_generator/i18n/__init__.py
streamlit_app_generator/i18n/translations_en.py
streamlit_app_generator/i18n/translations_pt_br.py
streamlit_app_generator/templates/.env.example
streamlit_app_generator/templates/__init__.py
streamlit_app_generator/templates/about_section.py
streamlit_app_generator/templates/secrets.toml.example
streamlit_app_generator/templates/__pycache__/__init__.cpython-312.pyc
streamlit_app_generator/templates/auth/__init__.py
streamlit_app_generator/templates/auth/login.py
streamlit_app_generator/templates/auth/login_basic.py
streamlit_app_generator/templates/auth/login_minimal.py
streamlit_app_generator/templates/auth/login_modern.py
streamlit_app_generator/templates/auth/session.py
streamlit_app_generator/templates/auth/session_manager.py
streamlit_app_generator/templates/auth/user_repository.py
streamlit_app_generator/templates/database/__init__.py
streamlit_app_generator/templates/database/base_connector.py
streamlit_app_generator/templates/database/mongodb.py
streamlit_app_generator/templates/database/mysql.py
streamlit_app_generator/templates/database/oracle.py
streamlit_app_generator/templates/database/postgresql.py
streamlit_app_generator/templates/database/redis.py
streamlit_app_generator/templates/database/sqlite.py
streamlit_app_generator/templates/layouts/__init__.py
streamlit_app_generator/templates/pages/__init__.py
streamlit_app_generator/utils/__init__.py
streamlit_app_generator/utils/helpers.py
streamlit_app_generator/utils/validators.py
streamlit_app_generator-1.0.2.dist-info/licenses/LICENSE
streamlit_app_generator-1.0.2.dist-info/METADATA
streamlit_app_generator-1.0.2.dist-info/WHEEL
streamlit_app_generator-1.0.2.dist-info/entry_points.txt
streamlit_app_generator-1.0.2.dist-info/top_level.txt
streamlit_app_generator-1.0.2.dist-info/RECORD
