Metadata-Version: 2.4
Name: streamlit-app-generator
Version: 1.0.2
Summary: Generate complete Streamlit applications with authentication and database templates
Home-page: https://github.com/leandrodalcortivo/streamlit-app-generator
Author: Leandro Meyer Dal Cortivo
Author-email: Leandro Meyer DC <lmdcorti@gmail.com>
License: MIT
Project-URL: Homepage, https://github.com/leandrodalcortivo/streamlit-app-generator
Project-URL: Repository, https://github.com/leandrodalcortivo/streamlit-app-generator
Project-URL: Documentation, https://github.com/leandrodalcortivo/streamlit-app-generator#readme
Project-URL: Bug Tracker, https://github.com/leandrodalcortivo/streamlit-app-generator/issues
Project-URL: Funding, https://github.com/leandrodalcortivo/streamlit-app-generator/blob/master/SUPPORT.md
Keywords: streamlit,generator,authentication,database,cli,template
Classifier: Development Status :: 5 - Production/Stable
Classifier: Intended Audience :: Developers
Classifier: Topic :: Software Development :: Code Generators
Classifier: Topic :: Software Development :: Libraries :: Python Modules
Classifier: License :: OSI Approved :: MIT License
Classifier: Programming Language :: Python :: 3
Classifier: Programming Language :: Python :: 3.8
Classifier: Programming Language :: Python :: 3.9
Classifier: Programming Language :: Python :: 3.10
Classifier: Programming Language :: Python :: 3.11
Classifier: Programming Language :: Python :: 3.12
Classifier: Operating System :: OS Independent
Requires-Python: >=3.8
License-File: LICENSE
Requires-Dist: streamlit>=1.28.0
Requires-Dist: click>=8.0.0
Requires-Dist: jinja2>=3.0.0
Requires-Dist: pyyaml>=6.0
Requires-Dist: bcrypt>=4.0.0
Requires-Dist: python-dotenv>=1.0.2
Requires-Dist: pydantic>=2.0.0
Provides-Extra: postgresql
Requires-Dist: psycopg2-binary>=2.9.0; extra == "postgresql"
Requires-Dist: sqlalchemy>=2.0.0; extra == "postgresql"
Provides-Extra: mysql
Requires-Dist: mysql-connector-python>=8.0.0; extra == "mysql"
Requires-Dist: sqlalchemy>=2.0.0; extra == "mysql"
Provides-Extra: mongodb
Requires-Dist: pymongo>=4.0.0; extra == "mongodb"
Provides-Extra: redis
Requires-Dist: redis>=5.0.0; extra == "redis"
Provides-Extra: oracle
Requires-Dist: oracledb>=2.0.0; extra == "oracle"
Provides-Extra: all-databases
Requires-Dist: psycopg2-binary>=2.9.0; extra == "all-databases"
Requires-Dist: mysql-connector-python>=8.0.0; extra == "all-databases"
Requires-Dist: pymongo>=4.0.0; extra == "all-databases"
Requires-Dist: redis>=5.0.0; extra == "all-databases"
Requires-Dist: oracledb>=2.0.0; extra == "all-databases"
Requires-Dist: sqlalchemy>=2.0.0; extra == "all-databases"
Provides-Extra: dev
Requires-Dist: pytest>=7.0.0; extra == "dev"
Requires-Dist: pytest-cov>=4.0.0; extra == "dev"
Requires-Dist: black>=23.0.0; extra == "dev"
Requires-Dist: flake8>=6.0.0; extra == "dev"
Requires-Dist: mypy>=1.0.2; extra == "dev"
Requires-Dist: isort>=5.12.0; extra == "dev"
Requires-Dist: pre-commit>=3.0.0; extra == "dev"
Dynamic: author
Dynamic: home-page
Dynamic: license-file
Dynamic: requires-python
